domino/__init__.py
domino/agg.py
domino/categorical_analysis.py
domino/core.py
domino/deseasonaliser.py
domino/filtering.py
domino/plsr.py
domino/prediction.py
domino/util.py
domino_composite-0.2591.dist-info/METADATA
domino_composite-0.2591.dist-info/WHEEL
domino_composite-0.2591.dist-info/top_level.txt
domino_composite-0.2591.dist-info/RECORD
