Metadata-Version: 2.1
Name: domino-composite
Version: 0.2591
Summary: A package for compositing atmospheric datasets
Home-page: https://github.com/joshdorrington/domino
Author: Josh Dorrington
Author-email: joshua.dorrington@kit.edu
License: bsd-3-clause
Requires-Dist: numpy (>=1.21)
Requires-Dist: pandas (>=1.4)
Requires-Dist: xarray (>=0.21.1)
Requires-Dist: scipy (>=1.7)
Requires-Dist: cftime (>=1.5)
